mthrottle/Throttle.py
mthrottle/__init__.py
mthrottle-0.0.1.dist-info/METADATA
mthrottle-0.0.1.dist-info/WHEEL
mthrottle-0.0.1.dist-info/licenses/LICENSE
mthrottle-0.0.1.dist-info/RECORD
