Metadata-Version: 2.1
Name: mthrottle
Version: 0.0.1
Summary: A simple and generic rate limiter to prevent too many function calls or http requests.
Project-URL: Homepage, https://github.com/BennyThadikaran/mThrottle
Project-URL: Bug Tracker, https://github.com/BennyThadikaran/mThrottle/issues
Author: Benny Thadikaran
License-File: LICENSE
Keywords: rate-limiter,throttle,throttle-requests,throttler
Classifier: License :: OSI Approved :: GNU General Public License v3 (GPLv3)
Classifier: Operating System :: OS Independent
Classifier: Programming Language :: Python :: 3
Requires-Python: >=3.7
